{
    "modelo": "Random Forest",
    "tipo": "Classifica\u00e7\u00e3o (Obesidade)",
    "data_salvamento": "2026-04-27T21:31:30.611960",
    "features_totais": 10,
    "features_selecionadas": [
        "Sexo biol\u00f3gico",
        "Idade em anos",
        "Hist\u00f3rico familiar de excesso de peso",
        "Frequ\u00eancia de consumo de vegetais",
        "N\u00famero de refei\u00e7\u00f5es principais",
        "Consumo de lanches entre refei\u00e7\u00f5es",
        "Consumo di\u00e1rio de \u00e1gua",
        "Frequ\u00eancia semanal de atividade f\u00edsica",
        "Tempo di\u00e1rio de uso de eletr\u00f4nicos",
        "Consumo de bebida alco\u00f3lica"
    ],
    "parametros_otimizados": {
        "n_estimators": 200,
        "max_depth": 12,
        "min_samples_split": 2,
        "min_samples_leaf": 1,
        "max_features": "sqrt",
        "bootstrap": true,
        "random_state": 42
    },
    "performance": {
        "acuracia_teste": 0.7825,
        "f1_score": 0.7797,
        "cv_media": 0.7714,
        "confianca_media": 70.17
    },
    "dados_treinamento": {
        "total_amostras_treino": 1688,
        "total_amostras_teste": 423,
        "classes": 7,
        "nomes_classes": [
            "Insufficient_Weight",
            "Normal_Weight",
            "Overweight_Level_I",
            "Overweight_Level_II",
            "Obesity_Type_I",
            "Obesity_Type_II",
            "Obesity_Type_III"
        ]
    }
}